pydactyl/__init__.py
pydactyl/dactyler/Constant.py
pydactyl/dactyler/Dactyler.py
pydactyl/dactyler/Hart.py
pydactyl/dactyler/Parncutt.py
pydactyl/dactyler/Sayegh.py
pydactyl/dactyler/__init__.py
pydactyl/dcorpus/ABCDHeader.py
pydactyl/dcorpus/DAnnotation.py
pydactyl/dcorpus/DCorpus.py
pydactyl/dcorpus/DEvaluation.py
pydactyl/dcorpus/DNote.py
pydactyl/dcorpus/DPart.py
pydactyl/dcorpus/DScore.py
pydactyl/dcorpus/DSegmenter.py
pydactyl/dcorpus/ManualDSegmenter.py
pydactyl/dcorpus/OneDSegmenter.py
pydactyl/dcorpus/__init__.py
test/TestConstant.py
test/__init__.py
test/ismir2018.py
test/test_abcd_header.py
test/test_d_corpus.py
test/test_hart.py
test/test_hart_k.py
test/test_interval.py
test/test_parncutt.py
test/test_rank.py
test/test_sayegh.py
test/test_segment.py
pydactyl-0.5.dist-info/LICENSE
pydactyl-0.5.dist-info/METADATA
pydactyl-0.5.dist-info/WHEEL
pydactyl-0.5.dist-info/top_level.txt
pydactyl-0.5.dist-info/RECORD
